Metadata-Version: 1.1
Name: orderedpy
Version: 0.0.2
Summary: Ordered version of the python list
Home-page: https://github.com/monzita/orderedpy
Author: Monika Ilieva
Author-email: hidden@hidden.com
License: MIT License
Keywords: orderedpy
Platform: UNKNOWN
Classifier: Development Status :: 3 - Alpha
Classifier: Programming Language :: Python :: 3.8
Classifier: Programming Language :: Python :: 3.9
Classifier: Programming Language :: Python :: 3 :: Only
